multidim_image_augmentation/__init__.py
multidim_image_augmentation/python/__init__.py
multidim_image_augmentation/python/ops/_augmentation_ops.so
multidim_image_augmentation/python/ops/augmentation_ops.py
multidim_image_augmentation/python/ops/__init__.py
multidim_image_augmentation-0.0.2.dist-info/RECORD
multidim_image_augmentation-0.0.2.dist-info/METADATA
multidim_image_augmentation-0.0.2.dist-info/LICENSE
multidim_image_augmentation-0.0.2.dist-info/top_level.txt
multidim_image_augmentation-0.0.2.dist-info/WHEEL
