Metadata-Version: 2.1
Name: multidim-image-augmentation
Version: 0.0.2
Summary: Pip installable fork of https://github.com/deepmind/multidim-image-augmentation
Home-page: UNKNOWN
Author: Diego Ardila
Author-email: diego@captionhealth.com
License: Apache 2.0
Keywords: tensorflow custom op machine learning
Platform: UNKNOWN
Classifier: Development Status :: 4 - Beta
Classifier: Intended Audience :: Developers
Classifier: Intended Audience :: Education
Classifier: Intended Audience :: Science/Research
Classifier: License :: OSI Approved :: Apache Software License
Classifier: Programming Language :: Python :: 2.7
Classifier: Programming Language :: Python :: 3.4
Classifier: Programming Language :: Python :: 3.5
Classifier: Programming Language :: Python :: 3.6
Classifier: Programming Language :: Python :: 3.7
Classifier: Programming Language :: Python :: 3.8
Classifier: Topic :: Scientific/Engineering :: Mathematics
Classifier: Topic :: Software Development :: Libraries :: Python Modules
Classifier: Topic :: Software Development :: Libraries
Requires-Dist: tensorflow (>=2.3.0)
